rentavle_sdk/__init__.py
rentavle_sdk/config.py
rentavle_sdk/api/__init__.py
rentavle_sdk/api/rentavle.py
rentavle_sdk/api/nft/__init__.py
rentavle_sdk/api/nft/nft_endpoints.py
rentavle_sdk/api/nft/responses.py
rentavle_sdk/utils/__init__.py
rentavle_sdk/utils/request.py
rentavle_sdk-0.1.3.dist-info/LICENSE
rentavle_sdk-0.1.3.dist-info/METADATA
rentavle_sdk-0.1.3.dist-info/WHEEL
rentavle_sdk-0.1.3.dist-info/top_level.txt
rentavle_sdk-0.1.3.dist-info/RECORD
