Metadata-Version: 2.1
Name: rentavle-sdk
Version: 0.1.3
Summary: A simple SDK for the Rentavle service
Home-page: https://github.com/rentavle/rentavle-sdk-python
Author: Rentavle
Author-email: supergravitycorp@gmail.com
Classifier: Development Status :: 3 - Alpha
Classifier: Intended Audience :: Developers
Classifier: License :: OSI Approved :: MIT License
Classifier: Programming Language :: Python :: 3
Classifier: Programming Language :: Python :: 3.6
Classifier: Programming Language :: Python :: 3.7
Classifier: Programming Language :: Python :: 3.8
Classifier: Programming Language :: Python :: 3.9
License-File: LICENSE
Requires-Dist: requests (>=2.25.0)
